pdynamics/__init__.py
pdynamics/crm.py
pdynamics-0.2.4.dist-info/LICENSE
pdynamics-0.2.4.dist-info/METADATA
pdynamics-0.2.4.dist-info/WHEEL
pdynamics-0.2.4.dist-info/top_level.txt
pdynamics-0.2.4.dist-info/RECORD
