Metadata-Version: 2.1
Name: pdynamics
Version: 0.2.4
Summary: Python connector for Microsoft Dynamics 365, supports AD, IFD and Online
Home-page: https://github.com/jiangweifeng/pdynamics
Author: Weifeng Jiang
Author-email: jiangweifeng@live.com
License: UNKNOWN
Platform: UNKNOWN
Classifier: Programming Language :: Python :: 3
Classifier: License :: OSI Approved :: MIT License
Classifier: Operating System :: OS Independent
